Rach/Rach.py
Rach/__init__.py
Rach-1.0.0.dist-info/LICENSE
Rach-1.0.0.dist-info/METADATA
Rach-1.0.0.dist-info/WHEEL
Rach-1.0.0.dist-info/top_level.txt
Rach-1.0.0.dist-info/RECORD
