Metadata-Version: 2.1
Name: Rach
Version: 1.0.0
Summary: Python client for Rach
Home-page: https://github.com/srinskit/RachPy
Author: srinskit
Author-email: srinskit.off@gmail.com
License: UNKNOWN
Platform: UNKNOWN
Classifier: Programming Language :: Python :: 3
Classifier: License :: OSI Approved :: MIT License
Classifier: Operating System :: OS Independent
